Second_Year/Third Sem/DSCO/Lab3/qn1.v
module qn1(input A,B,C,D, output f);

wire A1,C1,D1;
wire t1,t2,t3;
wire n1,n2,n3;

assign A1 = ~(A & A);
assign C1 = ~(C & C);
assign D1 = ~(D & D);

assign n1 = ~(A1 & B);
assign n2 = ~(C & D1);
assign n3 = ~(B & C1);

assign f = ~(n1 & n2 & n3);

endmodule

Second_Year/Third Sem/DSCO/Lab3/qn1_tb.v
`timescale 1ns/1ps
`include "qn1.v"

module qn1_tb();

reg A,B,C,D;
wire f;

qn1 one(A,B,C,D,f);

initial
begin
    $dumpfile("qn1.vcd");
    $dumpvars(0,qn1_tb);

    A=0;B=0;C=0;D=0;
    #10 A=0;B=0;C=0;D=1;
    #10 A=0;B=0;C=1;D=0;
    #10 A=0;B=0;C=1;D=1;

    #10 A=0;B=1;C=0;D=0;
    #10 A=0;B=1;C=0;D=1;
    #10 A=0;B=1;C=1;D=0;
    #10 A=0;B=1;C=1;D=1;

    #10 A=1;B=0;C=0;D=0;
    #10 A=1;B=0;C=0;D=1;
    #10 A=1;B=0;C=1;D=0;
    #10 A=1;B=0;C=1;D=1;

    #10 A=1;B=1;C=0;D=0;
    #10 A=1;B=1;C=0;D=1;
    #10 A=1;B=1;C=1;D=0;
    #10 A=1;B=1;C=1;D=1;

    #10
     $finish;
end

endmodule

Second_Year/Third Sem/DSCO/Lab3/qn1.vcd
$date
	Mon May 18 22:45:32 2026
$end
$version
	Icarus Verilog
$end
$timescale
	1ps
$end
$scope module qn1_tb $end
$var wire 1 ! f $end
$var reg 1 " A $end
$var reg 1 # B $end
$var reg 1 $ C $end
$var reg 1 % D $end
$scope module one $end
$var wire 1 " A $end
$var wire 1 & A1 $end
$var wire 1 # B $end
$var wire 1 $ C $end
$var wire 1 ' C1 $end
$var wire 1 % D $end
$var wire 1 ( D1 $end
$var wire 1 ! f $end
$var wire 1 ) n1 $end
$var wire 1 * n2 $end
$var wire 1 + n3 $end
$upscope $end
$upscope $end
$enddefinitions $end
$comment Show the parameter values. $end
$dumpall
$end
#0
$dumpvars
1+
1*
1)
1(
1'
1&
0%
0$
0#
0"
0!
$end
#10000
0(
1%
#20000
1!
0*
1(
0'
0%
1$
#30000
0!
1*
0(
1%
#40000
1!
0+
1(
1'
0)
0%
0$
1#
#50000
0(
1%
#60000
0*
1+
1(
0'
0%
1$
#70000
1*
0(
1%
#80000
0!
1(
1'
1)
0&
0%
0$
0#
1"
#90000
0(
1%
#100000
1!
0*
1(
0'
0%
1$
#110000
0!
1*
0(
1%
#120000
1!
0+
1(
1'
0%
0$
1#
#130000
0(
1%
#140000
1!
0*
1+
1(
0'
0%
1$
#150000
0!
1*
0(
1%
