Second_Year/Third Sem/DSCO/Lab3/qn2.v
module qn2(input A,B,C,D, output f);

wire B1,C1,D1;
wire t1;

assign B1 = ~(B | B);
assign C1 = ~(C | C);
assign D1 = ~(D | D);

assign t1 = ~(C1 | D1);

assign f = ~(B | t1);

endmodule

Second_Year/Third Sem/DSCO/Lab3/qn2_tb.v
`timescale 1ns/1ps
`include "qn2.v"

module qn2_tb();

reg A,B,C,D;
wire f;

qn2 two(A,B,C,D,f);

initial
begin
    $dumpfile("qn2.vcd");
    $dumpvars(0,qn2_tb);

    A=0;B=0;C=0;D=0;
    #10 A=0;B=0;C=0;D=1;
    #10 A=0;B=0;C=1;D=0;
    #10 A=0;B=0;C=1;D=1;

    #10 A=0;B=1;C=0;D=0;
    #10 A=0;B=1;C=0;D=1;
    #10 A=0;B=1;C=1;D=0;
    #10 A=0;B=1;C=1;D=1;

    #10 A=1;B=0;C=0;D=0;
    #10 A=1;B=0;C=0;D=1;
    #10 A=1;B=0;C=1;D=0;
    #10 A=1;B=0;C=1;D=1;

    #10 A=1;B=1;C=0;D=0;
    #10 A=1;B=1;C=0;D=1;
    #10 A=1;B=1;C=1;D=0;
    #10 A=1;B=1;C=1;D=1;

    #10 $finish;
end

endmodule

Second_Year/Third Sem/DSCO/Lab3/qn2.vcd
$date
	Mon May 18 22:45:41 2026
$end
$version
	Icarus Verilog
$end
$timescale
	1ps
$end
$scope module qn2_tb $end
$var wire 1 ! f $end
$var reg 1 " A $end
$var reg 1 # B $end
$var reg 1 $ C $end
$var reg 1 % D $end
$scope module two $end
$var wire 1 " A $end
$var wire 1 # B $end
$var wire 1 & B1 $end
$var wire 1 $ C $end
$var wire 1 ' C1 $end
$var wire 1 % D $end
$var wire 1 ( D1 $end
$var wire 1 ! f $end
$var wire 1 ) t1 $end
$upscope $end
$upscope $end
$enddefinitions $end
$comment Show the parameter values. $end
$dumpall
$end
#0
$dumpvars
0)
1(
1'
1&
0%
0$
0#
0"
1!
$end
#10000
0(
1%
#20000
1(
0'
0%
1$
#30000
0!
1)
0(
1%
#40000
0)
1(
1'
0&
0%
0$
1#
#50000
0(
1%
#60000
1(
0'
0%
1$
#70000
1)
0(
1%
#80000
1!
0)
1(
1'
1&
0%
0$
0#
1"
#90000
0(
1%
#100000
1(
0'
0%
1$
#110000
0!
1)
0(
1%
#120000
0)
1(
1'
0&
0%
0$
1#
#130000
0(
1%
#140000
1(
0'
0%
1$
#150000
1)
0(
1%
