Second_Year/Third Sem/DSCO/Lab3/qn3.v
module qn3(input A,B,C,D, output f);

wire A1,C1,t1,D1;

assign A1 = ~(A | A);
assign C1 = ~(C | C);

assign t1 = ~(A1 | C1);

assign D1 = ~(D | D);

assign f = ~(D1 | t1);

endmodule

Second_Year/Third Sem/DSCO/Lab3/qn3_tb.v
`timescale 1ns/1ps
`include "qn3.v"

module qn3_tb();

reg A,B,C,D;
wire f;

qn3 three(A,B,C,D,f);

initial
begin
    $dumpfile("qn3.vcd");
    $dumpvars(0,qn3_tb);

    A=0;B=0;C=0;D=0;
    #10 A=0;B=0;C=0;D=1;
    #10 A=0;B=0;C=1;D=0;
    #10 A=0;B=0;C=1;D=1;

    #10 A=0;B=1;C=0;D=0;
    #10 A=0;B=1;C=0;D=1;
    #10 A=0;B=1;C=1;D=0;
    #10 A=0;B=1;C=1;D=1;

    #10 A=1;B=0;C=0;D=0;
    #10 A=1;B=0;C=0;D=1;
    #10 A=1;B=0;C=1;D=0;
    #10 A=1;B=0;C=1;D=1;

    #10 A=1;B=1;C=0;D=0;
    #10 A=1;B=1;C=0;D=1;
    #10 A=1;B=1;C=1;D=0;
    #10 A=1;B=1;C=1;D=1;

    #10 $finish;
end

endmodule

Second_Year/Third Sem/DSCO/Lab3/qn3.vcd
$date
	Mon May 18 22:45:45 2026
$end
$version
	Icarus Verilog
$end
$timescale
	1ps
$end
$scope module qn3_tb $end
$var wire 1 ! f $end
$var reg 1 " A $end
$var reg 1 # B $end
$var reg 1 $ C $end
$var reg 1 % D $end
$scope module three $end
$var wire 1 " A $end
$var wire 1 & A1 $end
$var wire 1 # B $end
$var wire 1 $ C $end
$var wire 1 ' C1 $end
$var wire 1 % D $end
$var wire 1 ( D1 $end
$var wire 1 ! f $end
$var wire 1 ) t1 $end
$upscope $end
$upscope $end
$enddefinitions $end
$comment Show the parameter values. $end
$dumpall
$end
#0
$dumpvars
0)
1(
1'
1&
0%
0$
0#
0"
0!
$end
#10000
1!
0(
1%
#20000
0!
1(
0'
0%
1$
#30000
1!
0(
1%
#40000
0!
1(
1'
0%
0$
1#
#50000
1!
0(
1%
#60000
0!
1(
0'
0%
1$
#70000
1!
0(
1%
#80000
0!
1(
1'
0&
0%
0$
0#
1"
#90000
1!
0(
1%
#100000
0!
1)
1(
0'
0%
1$
#110000
0(
1%
#120000
0)
1(
1'
0%
0$
1#
#130000
1!
0(
1%
#140000
0!
1)
1(
0'
0%
1$
#150000
0(
1%
