Second_Year/Third Sem/DSCO/Lab5/mux16to1.v
module mux4to1 (
    input i0,
    input i1,
    input i2,
    input i3,
    input [1:0] sel,
    output y
);

assign y = (sel == 2'b00) ? i0 :
           (sel == 2'b01) ? i1 :
           (sel == 2'b10) ? i2 :
                            i3;

endmodule

module mux16to1 (
    input i0,
    input i1,
    input i2,
    input i3,
    input i4,
    input i5,
    input i6,
    input i7,
    input i8,
    input i9,
    input i10,
    input i11,
    input i12,
    input i13,
    input i14,
    input i15,
    input [3:0] sel,
    output y
);

wire w1, w2, w3, w4;

mux4to1 m1 (
    .i0(i0),
    .i1(i1),
    .i2(i2),
    .i3(i3),
    .sel(sel[1:0]),
    .y(w1)
);

mux4to1 m2 (
    .i0(i4),
    .i1(i5),
    .i2(i6),
    .i3(i7),
    .sel(sel[1:0]),
    .y(w2)
);

mux4to1 m3 (
    .i0(i8),
    .i1(i9),
    .i2(i10),
    .i3(i11),
    .sel(sel[1:0]),
    .y(w3)
);

mux4to1 m4 (
    .i0(i12),
    .i1(i13),
    .i2(i14),
    .i3(i15),
    .sel(sel[1:0]),
    .y(w4)
);

mux4to1 m5 (
    .i0(w1),
    .i1(w2),
    .i2(w3),
    .i3(w4),
    .sel(sel[3:2]),
    .y(y)
);

endmodule

Second_Year/Third Sem/DSCO/Lab5/mux16to1_d_tb.v
`timescale 1ns/1ps
`include "mux16to1.v"

module mux16to1_d_tb;

reg i0, i1, i2, i3;
reg i4, i5, i6, i7;
reg i8, i9, i10, i11;
reg i12, i13, i14, i15;

reg [3:0] sel;
wire y;

mux16to1 uut (
    .i0(i0), .i1(i1), .i2(i2), .i3(i3),
    .i4(i4), .i5(i5), .i6(i6), .i7(i7),
    .i8(i8), .i9(i9), .i10(i10), .i11(i11),
    .i12(i12), .i13(i13), .i14(i14), .i15(i15),
    .sel(sel),
    .y(y)
);

initial begin
    $dumpfile("mux16to1_d.vcd");
    $dumpvars(0, mux16to1_d_tb);

    i0=0;  i1=1;  i2=0;  i3=1;
    i4=0;  i5=1;  i6=0;  i7=1;
    i8=0;  i9=1;  i10=0; i11=1;
    i12=0; i13=1; i14=0; i15=1;

    sel=4'b0000; #10;
    sel=4'b0001; #10;
    sel=4'b0010; #10;
    sel=4'b0011; #10;
    sel=4'b0100; #10;
    sel=4'b0101; #10;
    sel=4'b0110; #10;
    sel=4'b0111; #10;
    sel=4'b1000; #10;
    sel=4'b1001; #10;
    sel=4'b1010; #10;
    sel=4'b1011; #10;
    sel=4'b1100; #10;
    sel=4'b1101; #10;
    sel=4'b1110; #10;
    sel=4'b1111; #10;

    $finish;
end

initial begin
    $monitor("sel=%b y=%b", sel, y);
end

endmodule

Second_Year/Third Sem/DSCO/Lab5/mux16to1_d.vcd
$date
	Sat May 23 12:05:28 2026
$end
$version
	Icarus Verilog
$end
$timescale
	1ps
$end
$scope module mux16to1_d_tb $end
$var wire 1 ! y $end
$var reg 1 " i0 $end
$var reg 1 # i1 $end
$var reg 1 $ i10 $end
$var reg 1 % i11 $end
$var reg 1 & i12 $end
$var reg 1 ' i13 $end
$var reg 1 ( i14 $end
$var reg 1 ) i15 $end
$var reg 1 * i2 $end
$var reg 1 + i3 $end
$var reg 1 , i4 $end
$var reg 1 - i5 $end
$var reg 1 . i6 $end
$var reg 1 / i7 $end
$var reg 1 0 i8 $end
$var reg 1 1 i9 $end
$var reg 4 2 sel [3:0] $end
$scope module uut $end
$var wire 1 " i0 $end
$var wire 1 # i1 $end
$var wire 1 $ i10 $end
$var wire 1 % i11 $end
$var wire 1 & i12 $end
$var wire 1 ' i13 $end
$var wire 1 ( i14 $end
$var wire 1 ) i15 $end
$var wire 1 * i2 $end
$var wire 1 + i3 $end
$var wire 1 , i4 $end
$var wire 1 - i5 $end
$var wire 1 . i6 $end
$var wire 1 / i7 $end
$var wire 1 0 i8 $end
$var wire 1 1 i9 $end
$var wire 4 3 sel [3:0] $end
$var wire 1 ! y $end
$var wire 1 4 w4 $end
$var wire 1 5 w3 $end
$var wire 1 6 w2 $end
$var wire 1 7 w1 $end
$scope module m1 $end
$var wire 1 " i0 $end
$var wire 1 # i1 $end
$var wire 1 * i2 $end
$var wire 1 + i3 $end
$var wire 2 8 sel [1:0] $end
$var wire 1 7 y $end
$upscope $end
$scope module m2 $end
$var wire 1 , i0 $end
$var wire 1 - i1 $end
$var wire 1 . i2 $end
$var wire 1 / i3 $end
$var wire 2 9 sel [1:0] $end
$var wire 1 6 y $end
$upscope $end
$scope module m3 $end
$var wire 1 0 i0 $end
$var wire 1 1 i1 $end
$var wire 1 $ i2 $end
$var wire 1 % i3 $end
$var wire 2 : sel [1:0] $end
$var wire 1 5 y $end
$upscope $end
$scope module m4 $end
$var wire 1 & i0 $end
$var wire 1 ' i1 $end
$var wire 1 ( i2 $end
$var wire 1 ) i3 $end
$var wire 2 ; sel [1:0] $end
$var wire 1 4 y $end
$upscope $end
$scope module m5 $end
$var wire 1 7 i0 $end
$var wire 1 6 i1 $end
$var wire 1 5 i2 $end
$var wire 1 4 i3 $end
$var wire 2 < sel [1:0] $end
$var wire 1 ! y $end
$upscope $end
$upscope $end
$upscope $end
$enddefinitions $end
$comment Show the parameter values. $end
$dumpall
$end
#0
$dumpvars
b0 <
b0 ;
b0 :
b0 9
b0 8
07
06
05
04
b0 3
b0 2
11
00
1/
0.
1-
0,
1+
0*
1)
0(
1'
0&
1%
0$
1#
0"
0!
$end
#10000
1!
17
16
15
14
b1 8
b1 9
b1 :
b1 ;
b1 2
b1 3
#20000
0!
07
06
05
04
b10 8
b10 9
b10 :
b10 ;
b10 2
b10 3
#30000
1!
17
16
15
14
b11 8
b11 9
b11 :
b11 ;
b11 2
b11 3
#40000
0!
07
06
05
04
b0 8
b0 9
b0 :
b0 ;
b1 <
b100 2
b100 3
#50000
1!
17
16
15
14
b1 8
b1 9
b1 :
b1 ;
b101 2
b101 3
#60000
0!
07
06
05
04
b10 8
b10 9
b10 :
b10 ;
b110 2
b110 3
#70000
1!
17
16
15
14
b11 8
b11 9
b11 :
b11 ;
b111 2
b111 3
#80000
0!
07
06
05
04
b0 8
b0 9
b0 :
b0 ;
b10 <
b1000 2
b1000 3
#90000
1!
17
16
15
14
b1 8
b1 9
b1 :
b1 ;
b1001 2
b1001 3
#100000
0!
07
06
05
04
b10 8
b10 9
b10 :
b10 ;
b1010 2
b1010 3
#110000
1!
17
16
15
14
b11 8
b11 9
b11 :
b11 ;
b1011 2
b1011 3
#120000
0!
07
06
05
04
b0 8
b0 9
b0 :
b0 ;
b11 <
b1100 2
b1100 3
#130000
1!
17
16
15
14
b1 8
b1 9
b1 :
b1 ;
b1101 2
b1101 3
#140000
0!
07
06
05
04
b10 8
b10 9
b10 :
b10 ;
b1110 2
b1110 3
#150000
1!
17
16
15
14
b11 8
b11 9
b11 :
b11 ;
b1111 2
b1111 3
