Second_Year/Third Sem/DSCO/Lab4/fulladder.v
module fulladder(
    input a,
    input b,
    input cin,
    output sum,
    output carry
);

assign sum = a ^ b ^ cin;
assign carry = (a & b) | (b & cin) | (a & cin);

endmodule

Second_Year/Third Sem/DSCO/Lab4/fulladder_tb.v
`timescale 1ns/1ps
`include "fulladder.v"

module fulladder_tb();

reg a, b, cin;
wire sum, carry;

fulladder fa( .a(a),.b(b),.cin(cin),.sum(sum),.carry(carry));

initial begin
    $dumpfile("fulladder.vcd");
    $dumpvars(0,fulladder_tb);
    $display("A B Cin | SUM CARRY");

    a=0; b=0; cin=0; #10;
    a=0; b=0; cin=1; #10;
    a=0; b=1; cin=0; #10;
    a=0; b=1; cin=1; #10;
    a=1; b=0; cin=0; #10;
    a=1; b=0; cin=1; #10;
    a=1; b=1; cin=0; #10;
    a=1; b=1; cin=1; #10;

    $finish;
end

initial begin
    $monitor("%b %b  %b  |  %b    %b", a, b, cin, sum, carry);
end

endmodule

Second_Year/Third Sem/DSCO/Lab4/fulladder.vcd
$date
	Sat May 23 00:57:33 2026
$end
$version
	Icarus Verilog
$end
$timescale
	1ps
$end
$scope module fulladder_tb $end
$var wire 1 ! sum $end
$var wire 1 " carry $end
$var reg 1 # a $end
$var reg 1 $ b $end
$var reg 1 % cin $end
$scope module fa $end
$var wire 1 # a $end
$var wire 1 $ b $end
$var wire 1 " carry $end
$var wire 1 % cin $end
$var wire 1 ! sum $end
$upscope $end
$upscope $end
$enddefinitions $end
$comment Show the parameter values. $end
$dumpall
$end
#0
$dumpvars
0%
0$
0#
0"
0!
$end
#10000
1!
1%
#20000
0%
1$
#30000
1"
0!
1%
#40000
0"
1!
0%
0$
1#
#50000
1"
0!
1%
#60000
0%
1$
#70000
1!
1%
