Second_Year/DSCO/Lab2/qn1_a.v
module qn1_a(input A,B,C,D, output f);

assign f = (C & D) |
           (~A & B) |
           (C & ~B) |
           (B & ~C & ~D);

endmodule

Second_Year/DSCO/Lab2/qn1_a_tb.v
`timescale 1ns/1ps
`include "qn1_a.v"
module qn1_a_tb();

reg a,b,c,d;
wire f;

qn1_a one_a(a,b,c,d,f);

initial
begin
    $dumpfile("qn1_a.vcd");
    $dumpvars(0,qn1_a_tb);

	
    a=0; b=0; c=0; d=0;
    #10 a=0; b=0; c=0; d=1;
    #10 a=0; b=0; c=1; d=0;
    #10 a=0; b=0; c=1; d=1;

    #10 a=0; b=1; c=0; d=0;
    #10 a=0; b=1; c=0; d=1;
    #10 a=0; b=1; c=1; d=0;
    #10 a=0; b=1; c=1; d=1;

    #10 a=1; b=0; c=0; d=0;
    #10 a=1; b=0; c=0; d=1;
    #10 a=1; b=0; c=1; d=0;
    #10 a=1; b=0; c=1; d=1;

    #10 a=1; b=1; c=0; d=0;
    #10 a=1; b=1; c=0; d=1;
    #10 a=1; b=1; c=1; d=0;
    #10 a=1; b=1; c=1; d=1;

    #10 $finish;
end

initial
begin
    $monitor("A=%b B=%b C=%b D=%b F=%b",a,b,c,d,f);
end

endmodule

Second_Year/Third Sem/DSCO/Lab2/qn1_a.vcd
$date
	Mon May 18 22:09:59 2026
$end
$version
	Icarus Verilog
$end
$timescale
	1ps
$end
$scope module qn1_a_tb $end
$var wire 1 ! f $end
$var reg 1 " a $end
$var reg 1 # b $end
$var reg 1 $ c $end
$var reg 1 % d $end
$scope module one_a $end
$var wire 1 " A $end
$var wire 1 # B $end
$var wire 1 $ C $end
$var wire 1 % D $end
$var wire 1 ! f $end
$upscope $end
$upscope $end
$enddefinitions $end
$comment Show the parameter values. $end
$dumpall
$end
#0
$dumpvars
0%
0$
0#
0"
0!
$end
#10000
1%
#20000
1!
0%
1$
#30000
1%
#40000
0%
0$
1#
#50000
1%
#60000
0%
1$
#70000
1%
#80000
0!
0%
0$
0#
1"
#90000
1%
#100000
1!
0%
1$
#110000
1%
#120000
0%
0$
1#
#130000
0!
1%
#140000
0%
1$
#150000
1!
1%
