Second_Year/DSCO/Lab2/qn3.v
module qn3(input x1,x2,x3,x4, output f);

assign f = (x1 & x2 & x3) |
           (x1 & x2 & x4) |
           (x1 & x3 & x4) |
           (x2 & x3 & x4);

endmodule

Second_Year/Third Sem/DSCO/Lab2/qn3_tb.v
`timescale 1ns/1ps
`include "qn3.v"

module qn3_tb();

reg x1,x2,x3,x4;
wire f;

qn3 three(x1,x2,x3,x4,f);

initial
begin
    $dumpfile("qn3.vcd");
    $dumpvars(0,qn3_tb);

    x1=0;x2=0;x3=0;x4=0;
    #10 x1=0;x2=0;x3=0;x4=1;
    #10 x1=0;x2=0;x3=1;x4=0;
    #10 x1=0;x2=0;x3=1;x4=1;

    #10 x1=0;x2=1;x3=0;x4=0;
    #10 x1=0;x2=1;x3=0;x4=1;
    #10 x1=0;x2=1;x3=1;x4=0;
    #10 x1=0;x2=1;x3=1;x4=1;

    #10 x1=1;x2=0;x3=0;x4=0;
    #10 x1=1;x2=0;x3=0;x4=1;
    #10 x1=1;x2=0;x3=1;x4=0;
    #10 x1=1;x2=0;x3=1;x4=1;

    #10 x1=1;x2=1;x3=0;x4=0;
    #10 x1=1;x2=1;x3=0;x4=1;
    #10 x1=1;x2=1;x3=1;x4=0;
    #10 x1=1;x2=1;x3=1;x4=1;

    #10 $finish;
end

initial
begin
    $monitor("x1=%b x2=%b x3=%b x4=%b f=%b",x1,x2,x3,x4,f);
end

endmodule

Second_Year/Third Sem/DSCO/Lab2/qn3.vcd
$date
	Mon May 18 22:22:36 2026
$end
$version
	Icarus Verilog
$end
$timescale
	1ps
$end
$scope module qn3_tb $end
$var wire 1 ! f $end
$var reg 1 " x1 $end
$var reg 1 # x2 $end
$var reg 1 $ x3 $end
$var reg 1 % x4 $end
$scope module three $end
$var wire 1 ! f $end
$var wire 1 " x1 $end
$var wire 1 # x2 $end
$var wire 1 $ x3 $end
$var wire 1 % x4 $end
$upscope $end
$upscope $end
$enddefinitions $end
$comment Show the parameter values. $end
$dumpall
$end
#0
$dumpvars
0%
0$
0#
0"
0!
$end
#10000
1%
#20000
0%
1$
#30000
1%
#40000
0%
0$
1#
#50000
1%
#60000
0%
1$
#70000
1!
1%
#80000
0!
0%
0$
0#
1"
#90000
1%
#100000
0%
1$
#110000
1!
1%
#120000
0!
0%
0$
1#
#130000
1!
1%
#140000
0%
1$
#150000
1%
